CHANGELOG.md
humplib/__init__.py
humplib/dumps.py
humplib/encoder.py
humplib/render.py
humplib/tools.py
humplib-0.1.5.dist-info/LICENSE
humplib-0.1.5.dist-info/WHEEL
humplib-0.1.5.dist-info/METADATA
humplib-0.1.5.dist-info/RECORD
